{
  "info": {
    "name": "World of Shadows — Suite · Users",
    "description": "Sub-suite for OpenAPI tag **Users** (generated).",
    "schema": "https://schema.getpostman.com/json/collection/v2.1.0/collection.json"
  },
  "item": [
    {
      "name": "Users",
      "description": "Generated requests grouped by OpenAPI tag **Users**.",
      "item": [
        {
          "name": "GET /users",
          "request": {
            "method": "GET",
            "header": [],
            "url": "{{backendBaseUrl}}{{backendApiPrefix}}/users",
            "description": "GET /users"
          },
          "response": []
        },
        {
          "name": "DELETE /users/{user_id}",
          "request": {
            "method": "DELETE",
            "header": [],
            "url": "{{backendBaseUrl}}{{backendApiPrefix}}/users/{user_id}",
            "description": "DELETE /users/{user_id}"
          },
          "response": []
        },
        {
          "name": "GET /users/{user_id}",
          "request": {
            "method": "GET",
            "header": [],
            "url": "{{backendBaseUrl}}{{backendApiPrefix}}/users/{user_id}",
            "description": "GET /users/{user_id}"
          },
          "response": []
        },
        {
          "name": "PUT /users/{user_id}",
          "request": {
            "method": "PUT",
            "header": [],
            "url": "{{backendBaseUrl}}{{backendApiPrefix}}/users/{user_id}",
            "description": "PUT /users/{user_id}"
          },
          "response": []
        },
        {
          "name": "GET /users/{user_id}/areas",
          "request": {
            "method": "GET",
            "header": [],
            "url": "{{backendBaseUrl}}{{backendApiPrefix}}/users/{user_id}/areas",
            "description": "GET /users/{user_id}/areas"
          },
          "response": []
        },
        {
          "name": "PUT /users/{user_id}/areas",
          "request": {
            "method": "PUT",
            "header": [],
            "url": "{{backendBaseUrl}}{{backendApiPrefix}}/users/{user_id}/areas",
            "description": "PUT /users/{user_id}/areas"
          },
          "response": []
        },
        {
          "name": "POST /users/{user_id}/ban",
          "request": {
            "method": "POST",
            "header": [],
            "url": "{{backendBaseUrl}}{{backendApiPrefix}}/users/{user_id}/ban",
            "description": "POST /users/{user_id}/ban"
          },
          "response": []
        },
        {
          "name": "GET /users/{user_id}/bookmarks",
          "request": {
            "method": "GET",
            "header": [],
            "url": "{{backendBaseUrl}}{{backendApiPrefix}}/users/{user_id}/bookmarks",
            "description": "GET /users/{user_id}/bookmarks"
          },
          "response": []
        },
        {
          "name": "PUT /users/{user_id}/password",
          "request": {
            "method": "PUT",
            "header": [],
            "url": "{{backendBaseUrl}}{{backendApiPrefix}}/users/{user_id}/password",
            "description": "PUT /users/{user_id}/password"
          },
          "response": []
        },
        {
          "name": "PUT /users/{user_id}/preferences",
          "request": {
            "method": "PUT",
            "header": [],
            "url": "{{backendBaseUrl}}{{backendApiPrefix}}/users/{user_id}/preferences",
            "description": "PUT /users/{user_id}/preferences"
          },
          "response": []
        },
        {
          "name": "GET /users/{user_id}/profile",
          "request": {
            "method": "GET",
            "header": [],
            "url": "{{backendBaseUrl}}{{backendApiPrefix}}/users/{user_id}/profile",
            "description": "GET /users/{user_id}/profile"
          },
          "response": []
        },
        {
          "name": "PATCH /users/{user_id}/role",
          "request": {
            "method": "PATCH",
            "header": [],
            "url": "{{backendBaseUrl}}{{backendApiPrefix}}/users/{user_id}/role",
            "description": "PATCH /users/{user_id}/role"
          },
          "response": []
        },
        {
          "name": "POST /users/{user_id}/unban",
          "request": {
            "method": "POST",
            "header": [],
            "url": "{{backendBaseUrl}}{{backendApiPrefix}}/users/{user_id}/unban",
            "description": "POST /users/{user_id}/unban"
          },
          "response": []
        }
      ]
    }
  ]
}
