{
  "info": {
    "name": "World of Shadows — Suite · Auth",
    "description": "Sub-suite for OpenAPI tag **Auth** (generated).",
    "schema": "https://schema.getpostman.com/json/collection/v2.1.0/collection.json"
  },
  "item": [
    {
      "name": "Auth",
      "description": "Generated requests grouped by OpenAPI tag **Auth**.",
      "item": [
        {
          "name": "POST /auth/forgot-password",
          "request": {
            "method": "POST",
            "header": [],
            "url": "{{backendBaseUrl}}{{backendApiPrefix}}/auth/forgot-password",
            "description": "POST /auth/forgot-password"
          },
          "response": []
        },
        {
          "name": "POST /auth/login",
          "request": {
            "method": "POST",
            "header": [],
            "url": "{{backendBaseUrl}}{{backendApiPrefix}}/auth/login",
            "description": "POST /auth/login"
          },
          "response": []
        },
        {
          "name": "POST /auth/logout",
          "request": {
            "method": "POST",
            "header": [],
            "url": "{{backendBaseUrl}}{{backendApiPrefix}}/auth/logout",
            "description": "POST /auth/logout"
          },
          "response": []
        },
        {
          "name": "GET /auth/me",
          "request": {
            "method": "GET",
            "header": [],
            "url": "{{backendBaseUrl}}{{backendApiPrefix}}/auth/me",
            "description": "GET /auth/me"
          },
          "response": []
        },
        {
          "name": "POST /auth/refresh",
          "request": {
            "method": "POST",
            "header": [],
            "url": "{{backendBaseUrl}}{{backendApiPrefix}}/auth/refresh",
            "description": "POST /auth/refresh"
          },
          "response": []
        },
        {
          "name": "POST /auth/register",
          "request": {
            "method": "POST",
            "header": [],
            "url": "{{backendBaseUrl}}{{backendApiPrefix}}/auth/register",
            "description": "POST /auth/register"
          },
          "response": []
        },
        {
          "name": "POST /auth/resend-verification",
          "request": {
            "method": "POST",
            "header": [],
            "url": "{{backendBaseUrl}}{{backendApiPrefix}}/auth/resend-verification",
            "description": "POST /auth/resend-verification"
          },
          "response": []
        },
        {
          "name": "POST /auth/reset-password",
          "request": {
            "method": "POST",
            "header": [],
            "url": "{{backendBaseUrl}}{{backendApiPrefix}}/auth/reset-password",
            "description": "POST /auth/reset-password"
          },
          "response": []
        }
      ]
    }
  ]
}
